ethereum_mcp/__about__.py
ethereum_mcp/__init__.py
ethereum_mcp/cli.py
ethereum_mcp-0.4.2.dist-info/licenses/LICENSE.txt
ethereum_mcp-0.4.2.dist-info/METADATA
ethereum_mcp-0.4.2.dist-info/WHEEL
ethereum_mcp-0.4.2.dist-info/entry_points.txt
ethereum_mcp-0.4.2.dist-info/top_level.txt
ethereum_mcp-0.4.2.dist-info/RECORD
