Metadata-Version: 2.4
Name: ethereum-mcp
Version: 0.4.2
Summary: Add your description here
Requires-Python: >=3.12
License-File: LICENSE.txt
Requires-Dist: fastmcp>=0.4.1
Requires-Dist: mcp>=1.6.0
Dynamic: license-file
